odoo/addons/product_analytic_donation/README.rst
odoo/addons/product_analytic_donation/__init__.py
odoo/addons/product_analytic_donation/__manifest__.py
odoo/addons/product_analytic_donation/i18n/de.po
odoo/addons/product_analytic_donation/i18n/es.po
odoo/addons/product_analytic_donation/i18n/it.po
odoo/addons/product_analytic_donation/i18n/product_analytic_donation.pot
odoo/addons/product_analytic_donation/models/__init__.py
odoo/addons/product_analytic_donation/models/account_analytic_distribution_model.py
odoo/addons/product_analytic_donation/readme/CONTRIBUTORS.rst
odoo/addons/product_analytic_donation/readme/DESCRIPTION.rst
odoo/addons/product_analytic_donation/readme/USAGE.rst
odoo/addons/product_analytic_donation/static/description/icon.png
odoo/addons/product_analytic_donation/static/description/index.html
odoo/addons/product_analytic_donation/tests/__init__.py
odoo/addons/product_analytic_donation/tests/test_donation.py
odoo_addon_product_analytic_donation-16.0.1.0.0.2.dist-info/METADATA
odoo_addon_product_analytic_donation-16.0.1.0.0.2.dist-info/WHEEL
odoo_addon_product_analytic_donation-16.0.1.0.0.2.dist-info/top_level.txt
odoo_addon_product_analytic_donation-16.0.1.0.0.2.dist-info/RECORD
